damv1env/__init__.py
damv1env/myenv.py
damv1env-0.0.3.dist-info/METADATA
damv1env-0.0.3.dist-info/WHEEL
damv1env-0.0.3.dist-info/top_level.txt
damv1env-0.0.3.dist-info/RECORD
